{
  "comment": [
    "Release branches of LLVM Embedded Toolchain for Arm will use",
    "specific revisions of the repos it depends on. This file provides",
    "a single source of truth for which revisions to use that can be",
    "queried by CMake and other automation software."
  ],
  "repos": {
    "llvm-project": {
      "comment": "tagType can be branch, tag or commithash",
      "tagType": "tag",
      "tag": "llvmorg-19.1.5"
    },
    "picolibc": {
      "tagType": "commithash",
      "tag": "e434fa1f41a83a888d6498922ab7f140011933d1"
    },
    "newlib": {
      "tagType": "tag",
      "tag": "newlib-4.1.0"
    }
  }
}
